[{"id":"1761330030456","name":"STORES","createdAt":1761330030456,"updatedAt":1761762669638,"deviceId":"device_1764180864222_utrn1yt4q","outletType":"production","location":"HO"},{"id":"1761330036866","name":"THE CAKERY","createdAt":1761330036866,"updatedAt":1761537180237,"deviceId":"device_1764180864222_utrn1yt4q","outletType":"sales","location":"The Cakery"},{"id":"1761330047830","name":"THE ENGLISH CAKE COMPANY - SHANGRI-LA","createdAt":1761330047830,"updatedAt":1761919440812,"deviceId":"device_1764180864222_utrn1yt4q","location":"OGF","outletType":"sales"},{"id":"1761368954232","name":"THE ENGLISH CAKE COMPANY - HAVELOCK CITY MALL","location":"HCM","createdAt":1761368954233,"updatedAt":1761508214083,"deviceId":"device_1764180864222_utrn1yt4q","outletType":"sales"},{"id":"1761369004091","name":"THE CAKERY- GALLE","createdAt":1761369004091,"updatedAt":1761589445171,"deviceId":"device_1764180864222_utrn1yt4q","outletType":"sales","location":"Galle"},{"id":"1761369347597","name":"La Latheria","location":"Battaramulla","createdAt":1761369347597,"updatedAt":1761508222053,"deviceId":"device_1764180864222_utrn1yt4q","outletType":"sales"},{"id":"1761154647569","name":"04-KITCHEN 01","location":"Baking Kitchen","createdAt":1761154647569,"updatedAt":1761506281288,"deviceId":"device_1764180864222_utrn1yt4q","outletType":"production"},{"id":"outlet-1764175939771-72tlqoevg-6","name":"04-KITCHEN 01","location":"Baking Kitchen","outletType":"production","createdAt":1764175939771,"updatedAt":1764175939771,"deviceId":"device_1764180864222_utrn1yt4q"},{"id":"outlet-1764176540997-zowxrsbxc-0","name":"STORES","location":"HO","outletType":"production","createdAt":1764176540997,"updatedAt":1764176540997,"deviceId":"device_1764180864222_utrn1yt4q"},{"id":"outlet-1764176540997-3nex44i4o-1","name":"THE CAKERY","location":"The Cakery","outletType":"sales","createdAt":1764176540997,"updatedAt":1764176540997,"deviceId":"device_1764180864222_utrn1yt4q"},{"id":"outlet-1764176540997-dhg7xyzfk-2","name":"THE ENGLISH CAKE COMPANY - SHANGRI-LA","location":"OGF","outletType":"sales","createdAt":1764176540997,"updatedAt":1764176540997,"deviceId":"device_1764180864222_utrn1yt4q"},{"id":"outlet-1764176540997-yajd3n1bj-3","name":"THE ENGLISH CAKE COMPANY - HAVELOCK CITY MALL","location":"HCM","outletType":"sales","createdAt":1764176540997,"updatedAt":1764176540997,"deviceId":"device_1764180864222_utrn1yt4q"},{"id":"outlet-1764176540997-bcbquxusv-4","name":"THE CAKERY- GALLE","location":"Galle","outletType":"sales","createdAt":1764176540997,"updatedAt":1764176540997,"deviceId":"device_1764180864222_utrn1yt4q"},{"id":"outlet-1764176540997-l74yxxn45-5","name":"La Latheria","location":"Battaramulla","outletType":"sales","createdAt":1764176540997,"updatedAt":1764176540997,"deviceId":"device_1764180864222_utrn1yt4q"}]